best/__init__.py
best/integration/__init__.py
best/unit/__init__.py
best/unit/conftest.py
best/unit/test_glue_session.py
best/unit/test_glue_session_demo.py
best/unit/test_session_apis.py
gluefactory-100.0.0.dist-info/LICENSE.txt
gluefactory-100.0.0.dist-info/METADATA
gluefactory-100.0.0.dist-info/WHEEL
gluefactory-100.0.0.dist-info/top_level.txt
gluefactory-100.0.0.dist-info/RECORD
