Metadata-Version: 2.1
Name: gluefactory
Version: 100.0.0
Summary: sdfsdf sdafaf safafa sfsdf
Home-page: UNKNOWN
Author: sharmajiii
Author-email: sharmaji@ict.com
License: UNKNOWN
Platform: UNKNOWN
Classifier: Programming Language :: Python :: 3
Classifier: License :: OSI Approved :: MIT License
Classifier: Operating System :: OS Independent
License-File: LICENSE.txt
